README.md
pyproject.toml
setup.py
muzne/__init__.py
muzne.egg-info/PKG-INFO
muzne.egg-info/SOURCES.txt
muzne.egg-info/dependency_links.txt
muzne.egg-info/entry_points.txt
muzne.egg-info/requires.txt
muzne.egg-info/top_level.txt